scrapy_gui/__init__.py
scrapy_gui/browser.py
scrapy_gui/load_selector.py
scrapy_gui/browser_window/__init__.py
scrapy_gui/browser_window/browser.py
scrapy_gui/browser_window/images/back.png
scrapy_gui/browser_window/images/empty.png
scrapy_gui/browser_window/images/forward.png
scrapy_gui/browser_window/images/loader.gif
scrapy_gui/utils_ui/__init__.py
scrapy_gui/utils_ui/errors.py
scrapy_gui/utils_ui/parser.py
scrapy_gui/utils_ui/text_viewer.py
scrapy_gui/utils_ui/tools_tab_ui.py
scrapy_GUI-1.2.dist-info/LICENSE
scrapy_GUI-1.2.dist-info/METADATA
scrapy_GUI-1.2.dist-info/WHEEL
scrapy_GUI-1.2.dist-info/top_level.txt
scrapy_GUI-1.2.dist-info/RECORD
