Metadata-Version: 2.1
Name: scrapy-GUI
Version: 1.2
Summary: A package for offering UI tools for building scrapy queries
Home-page: https://github.com/further-reading/scraping-browser
Author: Roy Healy
Author-email: roy.healy87@gmail.com
License: UNKNOWN
Platform: UNKNOWN
Classifier: Programming Language :: Python :: 3
Classifier: License :: OSI Approved :: MIT License
Classifier: Operating System :: OS Independent
Requires-Python: >=3.6
